{
    "locals": {
        "databricks_dbfs_file_for_each_var": {
            "/tests/empty.sh": {
                "content_b64_md5": "${md5(filebase64(pathexpand(\"databricks_dbfs_file_tests_empty_sh\")))}",
                "mkdirs": "true",
                "overwrite": "true",
                "path": "/tests/empty.sh",
                "source": "${pathexpand(\"databricks_dbfs_file_tests_empty_sh\")}",
                "validate_remote_file": "true"
            },
            "/tests/library.jar": {
                "content_b64_md5": "${md5(filebase64(pathexpand(\"databricks_dbfs_file_tests_library_jar\")))}",
                "mkdirs": "true",
                "overwrite": "true",
                "path": "/tests/library.jar",
                "source": "${pathexpand(\"databricks_dbfs_file_tests_library_jar\")}",
                "validate_remote_file": "true"
            },
            "/tests/networkx-2.5-py3-none-any.whl": {
                "content_b64_md5": "${md5(filebase64(pathexpand(\"databricks_dbfs_file_tests_networkx_2_5_py3_none_any_whl\")))}",
                "mkdirs": "true",
                "overwrite": "true",
                "path": "/tests/networkx-2.5-py3-none-any.whl",
                "source": "${pathexpand(\"databricks_dbfs_file_tests_networkx_2_5_py3_none_any_whl\")}",
                "validate_remote_file": "true"
            },
            "/tests/py_code.py": {
                "content_b64_md5": "${md5(filebase64(pathexpand(\"databricks_dbfs_file_tests_py_code_py\")))}",
                "mkdirs": "true",
                "overwrite": "true",
                "path": "/tests/py_code.py",
                "source": "${pathexpand(\"databricks_dbfs_file_tests_py_code_py\")}",
                "validate_remote_file": "true"
            },
            "/tests/py_code1.py": {
                "content_b64_md5": "${md5(filebase64(pathexpand(\"databricks_dbfs_file_tests_py_code1_py\")))}",
                "mkdirs": "true",
                "overwrite": "true",
                "path": "/tests/py_code1.py",
                "source": "${pathexpand(\"databricks_dbfs_file_tests_py_code1_py\")}",
                "validate_remote_file": "true"
            },
            "/tests/py_code2.py": {
                "content_b64_md5": "${md5(filebase64(pathexpand(\"databricks_dbfs_file_tests_py_code2_py\")))}",
                "mkdirs": "true",
                "overwrite": "true",
                "path": "/tests/py_code2.py",
                "source": "${pathexpand(\"databricks_dbfs_file_tests_py_code2_py\")}",
                "validate_remote_file": "true"
            }
        }
    },
    "resource": {
        "databricks_dbfs_file": {
            "databricks_dbfs_file": {
                "content_b64_md5": "${each.value.content_b64_md5}",
                "for_each": "${local.databricks_dbfs_file_for_each_var}",
                "mkdirs": "${each.value.mkdirs}",
                "overwrite": "${each.value.overwrite}",
                "path": "${each.value.path}",
                "source": "${each.value.source}",
                "validate_remote_file": "${each.value.validate_remote_file}"
            }
        }
    }
}